uk_national_health_service_number/__init__.py
uk_national_health_service_number/_internal.py
uk_national_health_service_number/core.py
uk_national_health_service_number-0.1.6.dist-info/METADATA
uk_national_health_service_number-0.1.6.dist-info/WHEEL
uk_national_health_service_number-0.1.6.dist-info/RECORD
